promptEngine/__init__.py
promptEngine/guiNumberChoice.py
promptEngine/guiSingleSelectChoice.py
promptEngine/guiTextBoxChoice.py
promptEngine/gui_warnings/__init__.py
promptEngine/gui_warnings/guiCustomWarning.py
promptEngine/gui_warnings/guiOkWarning.py
promptEngine/gui_warnings/guiYesNoWarning.py
promptEngine-0.0.1.dist-info/METADATA
promptEngine-0.0.1.dist-info/WHEEL
promptEngine-0.0.1.dist-info/top_level.txt
promptEngine-0.0.1.dist-info/RECORD
